seafile_nautilus/__init__.py
seafile_nautilus/__version__.py
seafile_nautilus/main.py
seafile_nautilus/pyzenity.py
seafile_nautilus/seafile.py
seafile_nautilus/icons/icon.png
seafile_nautilus/icons/icon.svg
seafile_nautilus/locales/fr/LC_MESSAGES/messages.mo
seafile_nautilus/locales/fr/LC_MESSAGES/messages.po
seafile_nautilus-0.1.3.post1.dist-info/LICENSE
seafile_nautilus-0.1.3.post1.dist-info/METADATA
seafile_nautilus-0.1.3.post1.dist-info/WHEEL
seafile_nautilus-0.1.3.post1.dist-info/entry_points.txt
seafile_nautilus-0.1.3.post1.dist-info/top_level.txt
seafile_nautilus-0.1.3.post1.dist-info/RECORD
