Metadata-Version: 2.1
Name: seafile-nautilus
Version: 0.1.3.post1
Summary: Seafile script for gnome-files (nautilus)
Home-page: https://gitlab.com/vinraspa/seafile-nautilus
Author: Vincent Raspal
License: MIT
Classifier: Development Status :: 5 - Production/Stable
Classifier: Operating System :: POSIX :: Linux
Classifier: Environment :: X11 Applications :: Gnome
Classifier: Intended Audience :: End Users/Desktop
Classifier: License :: OSI Approved :: MIT License
Classifier: Programming Language :: Python :: 3.8
License-File: LICENSE
Requires-Dist: requests
